sentropy/S_2b_df_after_removing_zero_abundance_species.csv
sentropy/__init__.py
sentropy/__main__.py
sentropy/abundance.py
sentropy/backend.py
sentropy/components.py
sentropy/exceptions.py
sentropy/log.py
sentropy/parameters.py
sentropy/powermean.py
sentropy/ray.py
sentropy/sentropy.py
sentropy/set.py
sentropy/similarity.py
sentropy/tests/S_2b_df_after_removing_zero_abundance_species.csv
sentropy/tests/mockray.py
sentropy/tests/mockray_test.py
sentropy/tests/ray_test.py
sentropy/tests/base_tests/abundance_test.py
sentropy/tests/base_tests/backend_test.py
sentropy/tests/base_tests/components_test.py
sentropy/tests/base_tests/main_test.py
sentropy/tests/base_tests/parameters_test.py
sentropy/tests/base_tests/powermean_test.py
sentropy/tests/base_tests/sentropy_test.py
sentropy/tests/base_tests/set_test.py
sentropy/tests/base_tests/similarity_test.py
sentropy/tests/base_tests/test_material/S_2b.csv
sentropy/tests/base_tests/test_material/counts_2b_1.csv
sentropy/tests/base_tests/test_material/counts_2b_2.csv
sentropy-1.0.5.dist-info/METADATA
sentropy-1.0.5.dist-info/WHEEL
sentropy-1.0.5.dist-info/licenses/LICENSE
sentropy-1.0.5.dist-info/RECORD
